LICENSE
MANIFEST.in
NOTICE
README.md
setup.py
deploy/requirements.txt
label_studio/__init__.py
label_studio/constants.py
label_studio/feature_flags.json
label_studio/manage.py
label_studio/pytest.ini
label_studio/server.py
label_studio/sitecustomize.py
label_studio/annotation_templates/CONTRIBUTING.md
label_studio/annotation_templates/README.md
label_studio/annotation_templates/groups.txt
label_studio/annotation_templates/audio-speech-processing/automatic-speech-recognition/config.xml
label_studio/annotation_templates/audio-speech-processing/automatic-speech-recognition/config.yml
label_studio/annotation_templates/audio-speech-processing/automatic-speech-recognition-using-segments/config.xml
label_studio/annotation_templates/audio-speech-processing/automatic-speech-recognition-using-segments/config.yml
label_studio/annotation_templates/audio-speech-processing/conversational-analysis/config.yml
label_studio/annotation_templates/audio-speech-processing/intent-classification/config.xml
label_studio/annotation_templates/audio-speech-processing/intent-classification/config.yml
label_studio/annotation_templates/audio-speech-processing/signal-quality-detection/config.xml
label_studio/annotation_templates/audio-speech-processing/signal-quality-detection/config.yml
label_studio/annotation_templates/audio-speech-processing/sound-event-detection/config.xml
label_studio/annotation_templates/audio-speech-processing/sound-event-detection/config.yml
label_studio/annotation_templates/audio-speech-processing/speaker-segmentation/config.xml
label_studio/annotation_templates/audio-speech-processing/speaker-segmentation/config.yml
label_studio/annotation_templates/audio-speech-processing/speech-transcription/config.yml
label_studio/annotation_templates/computer-vision/image-captioning/config.yml
label_studio/annotation_templates/computer-vision/image-classification/config.yml
label_studio/annotation_templates/computer-vision/inventory-tracking/config.yml
label_studio_mmri.egg-info/PKG-INFO
label_studio_mmri.egg-info/SOURCES.txt
label_studio_mmri.egg-info/dependency_links.txt
label_studio_mmri.egg-info/entry_points.txt
label_studio_mmri.egg-info/requires.txt
label_studio_mmri.egg-info/top_level.txt