Metadata-Version: 2.1
Name: label-studio-mmri
Version: 1.8.2.dev0
Summary: Label Studio annotation tool
Home-page: https://github.com/heartexlabs/label-studio
Author: zen.gard
Author-email: zen.gard@aiai.com
Classifier: Programming Language :: Python :: 3
Classifier: License :: OSI Approved :: Apache Software License
Classifier: Operating System :: OS Independent
Requires-Python: >=3.6
Provides-Extra: mysql
License-File: LICENSE
License-File: NOTICE
